[
  {
    "id": 572,
    "level": "Wasteland",
    "location": "Barren Lands",
    "types": [
      "Camp"
    ],
    "title": "Hidden Path Supply Camp",
    "description": {
      "type": "text",
      "content": "As soon as you enter the area. However, you need to restore power at the Solar Tower to use it (side quest, “Reboot”)."
    },
    "display_order": 1,
    "images": [
      {
        "url": "/assets/images/Wasteland/1-BarrenLands/1-Supply Camp-Hidden Path.1.jpg",
        "alt": "Hidden Path Supply Camp",
        "order": 1
      },
      {
        "url": "/assets/images/Wasteland/1-BarrenLands/1-Supply Camp-Hidden Path.2.jpg",
        "alt": "Hidden Path Supply Camp",
        "order": 2
      }
    ]
  },
  {
    "id": 573,
    "level": "Wasteland",
    "location": "Barren Lands",
    "types": [
      "Memorystick"
    ],
    "title": "Memorystick - Amanda's Memory",
    "description": {
      "type": "text",
      "content": "From the supply camp, head southwest and there'll be a human corpse as the area opens up a little"
    },
    "display_order": 2,
    "images": [
      {
        "url": "/assets/images/Wasteland/1-BarrenLands/2-Memorystick-Amanda's Memory.1.jpg",
        "alt": "Memorystick (Amanda's Memory)",
        "order": 1
      },
      {
        "url": "/assets/images/Wasteland/1-BarrenLands/2-Memorystick-Amanda's Memory.2.jpg",
        "alt": "Memorystick (Amanda's Memory)",
        "order": 2
      }
    ]
  },
  {
    "id": 574,
    "level": "Wasteland",
    "location": "Barren Lands",
    "types": [
      "Memorystick"
    ],
    "title": "Memorystick - Donna's Memory",
    "description": {
      "type": "text",
      "content": "The corpse next to the previous memorystick is actually part of the “Missing Wife” Request. Interact to get this memorystick."
    },
    "display_order": 3,
    "images": [
      {
        "url": "/assets/images/Wasteland/1-BarrenLands/3-Memorystick-Donna's Memory.1.jpg",
        "alt": "Memorystick (Donna's Memory)",
        "order": 1
      },
      {
        "url": "/assets/images/Wasteland/1-BarrenLands/3-Memorystick-Donna's Memory.2.jpg",
        "alt": "Memorystick (Donna's Memory)",
        "order": 2
      }
    ]
  },
  {
    "id": 575,
    "level": "Wasteland",
    "location": "Barren Lands",
    "types": [
      "Supply Box"
    ],
    "title": "Legion Supply Box",
    "description": {
      "type": "text",
      "content": "Just slightly southwest from the previous memorysticks."
    },
    "display_order": 4,
    "images": [
      {
        "url": "/assets/images/Wasteland/1-BarrenLands/4-Legion Supply Box.1.jpg",
        "alt": "Legion Supply Box",
        "order": 1
      },
      {
        "url": "/assets/images/Wasteland/1-BarrenLands/4-Legion Supply Box.2.jpg",
        "alt": "Legion Supply Box",
        "order": 2
      }
    ]
  },
  {
    "id": 576,
    "level": "Wasteland",
    "location": "Barren Lands",
    "types": [
      "Document"
    ],
    "title": "Series - The Xion #2",
    "description": {
      "type": "text",
      "content": "East of the supply camp is a robot who drops this document."
    },
    "display_order": 5,
    "images": [
      {
        "url": "/assets/images/Wasteland/1-BarrenLands/5-Robot-Documents-Series-The Xion 2.1.jpg",
        "alt": "Document - Series - The Xion #2",
        "order": 1
      },
      {
        "url": "/assets/images/Wasteland/1-BarrenLands/5-Robot-Documents-Series-The Xion 2.2.jpg",
        "alt": "Document - Series - The Xion #2",
        "order": 2
      }
    ]
  },
  {
    "id": 577,
    "level": "Wasteland",
    "location": "Barren Lands",
    "types": [
      "Memorystick"
    ],
    "title": "Memorystick - Citizen 439's Resignation",
    "description": {
      "type": "text",
      "content": "Southeast of the Hidden Path supply camp is a large dead tree with a human corpse at its base."
    },
    "display_order": 6,
    "images": [
      {
        "url": "/assets/images/Wasteland/1-BarrenLands/6-Memorystick-Citizen 439's Resignation.1.jpg",
        "alt": "Memorystick (Citizen 439's Resignation)",
        "order": 1
      },
      {
        "url": "/assets/images/Wasteland/1-BarrenLands/6-Memorystick-Citizen 439's Resignation.2.jpg",
        "alt": "Memorystick (Citizen 439's Resignation)",
        "order": 2
      }
    ]
  },
  {
    "id": 578,
    "level": "Wasteland",
    "location": "Barren Lands",
    "types": [
      "Supply Box"
    ],
    "title": "Legion Supply Box",
    "description": {
      "type": "text",
      "content": "East of the previous memorystick."
    },
    "display_order": 7,
    "images": [
      {
        "url": "/assets/images/Wasteland/1-BarrenLands/7-Legion Supply Box.1.jpg",
        "alt": "Legion Supply Box",
        "order": 1
      },
      {
        "url": "/assets/images/Wasteland/1-BarrenLands/7-Legion Supply Box.2.jpg",
        "alt": "Legion Supply Box",
        "order": 2
      }
    ]
  },
  {
    "id": 579,
    "level": "Wasteland",
    "location": "Barren Lands",
    "types": [
      "Memorystick"
    ],
    "title": "Memorystick - Sentinel 78's Consolation",
    "description": {
      "type": "text",
      "content": "Just slightly southeast of the waypoint, behind a massive steel girder."
    },
    "display_order": 8,
    "images": [
      {
        "url": "/assets/images/Wasteland/1-BarrenLands/9-Memorystick-Sentinel 78's Consolation.1.jpg",
        "alt": "Memorystick (Sentinel 78's Consolation)",
        "order": 1
      },
      {
        "url": "/assets/images/Wasteland/1-BarrenLands/9-Memorystick-Sentinel 78's Consolation.2.jpg",
        "alt": "Memorystick (Sentinel 78's Consolation)",
        "order": 2
      }
    ]
  },
  {
    "id": 580,
    "level": "Wasteland",
    "location": "Barren Lands",
    "types": [
      "Supply Box"
    ],
    "title": "Legion Supply Box",
    "description": {
      "type": "text",
      "content": "Not far south from the Waypoint (northeast of the Barren Land Legion Camp)."
    },
    "display_order": 9,
    "images": [
      {
        "url": "/assets/images/Wasteland/1-BarrenLands/10-Legion Supply Box.1.jpg",
        "alt": "Legion Supply Box",
        "order": 1
      },
      {
        "url": "/assets/images/Wasteland/1-BarrenLands/10-Legion Supply Box.2.jpg",
        "alt": "Legion Supply Box",
        "order": 2
      }
    ]
  },
  {
    "id": 581,
    "level": "Wasteland",
    "location": "Barren Lands",
    "types": [
      "Camp"
    ],
    "title": "Barren Land Camp",
    "description": {
      "type": "text",
      "content": "Southwest of the previous supply box is the Barren Land Legion Camp."
    },
    "display_order": 10,
    "images": [
      {
        "url": "/assets/images/Wasteland/1-BarrenLands/11-Legion Camp.1.jpg",
        "alt": "Barren Land Camp",
        "order": 1
      },
      {
        "url": "/assets/images/Wasteland/1-BarrenLands/11-Legion Camp.2.jpg",
        "alt": "Barren Land Camp",
        "order": 2
      }
    ]
  },
  {
    "id": 582,
    "level": "Wasteland",
    "location": "Barren Lands",
    "types": [
      "Memorystick"
    ],
    "title": "Memorystick - Scavenger 160's Advice",
    "description": {
      "type": "text",
      "content": "Just northwest of the Barren Land Legion Camp is a Hedgeboar by two corpses."
    },
    "display_order": 11,
    "images": [
      {
        "url": "/assets/images/Wasteland/1-BarrenLands/12-Memorystick-Scavenger 160's Advice.1.jpg",
        "alt": "Memorystick (Scavenger 160's Advice)",
        "order": 1
      },
      {
        "url": "/assets/images/Wasteland/1-BarrenLands/12-Memorystick-Scavenger 160's Advice.2.jpg",
        "alt": "Memorystick (Scavenger 160's Advice)",
        "order": 2
      }
    ]
  },
  {
    "id": 583,
    "level": "Wasteland",
    "location": "Barren Lands",
    "types": [
      "Memorystick"
    ],
    "title": "Memorystick - Scavenger 102's Decision",
    "description": {
      "type": "text",
      "content": "The other corpse is next to the previous Memorystick."
    },
    "display_order": 12,
    "images": [
      {
        "url": "/assets/images/Wasteland/1-BarrenLands/13-Memorystick-Scavenger 102's Decision.1.jpg",
        "alt": "Memorystick (Scavenger 102's Decision)",
        "order": 1
      },
      {
        "url": "/assets/images/Wasteland/1-BarrenLands/13-Memorystick-Scavenger 102's Decision.2.jpg",
        "alt": "Memorystick (Scavenger 102's Decision)",
        "order": 2
      }
    ]
  },
  {
    "id": 584,
    "level": "Wasteland",
    "location": "Barren Lands",
    "types": [
      "Memorystick"
    ],
    "title": "Memorystick (Legionnaire 311's Resolution)",
    "description": {
      "type": "text",
      "content": "Slumped up against the west side of the Solar Tower."
    },
    "display_order": 13,
    "images": [
      {
        "url": "/assets/images/Wasteland/1-BarrenLands/14-Memorystick-Legionnaire 311's Resolution.1.jpg",
        "alt": "Memorystick (Legionnaire 311's Resolution)",
        "order": 1
      },
      {
        "url": "/assets/images/Wasteland/1-BarrenLands/14-Memorystick-Legionnaire 311's Resolution.2.jpg",
        "alt": "Memorystick (Legionnaire 311's Resolution)",
        "order": 2
      }
    ]
  },
  {
    "id": 585,
    "level": "Wasteland",
    "location": "Barren Lands",
    "types": [
      "Exospine"
    ],
    "title": "Camouflage-Type Exospine",
    "description": {
      "type": "text",
      "content": "At the top of the Solar Tower, in the western area of the Wasteland."
    },
    "display_order": 14,
    "images": [
      {
        "url": "/assets/images/Wasteland/1-BarrenLands/15-Camouflage-Type Exospine.1.jpg",
        "alt": "Camouflage-Type Exospine",
        "order": 1
      },
      {
        "url": "/assets/images/Wasteland/1-BarrenLands/15-Camouflage-Type Exospine.2.jpg",
        "alt": "Camouflage-Type Exospine",
        "order": 2
      }
    ]
  },
  {
    "id": 586,
    "level": "Wasteland",
    "location": "Barren Lands",
    "types": [
      "Memorystick"
    ],
    "title": "Memorystick (Legionnaire 323's Warning)",
    "description": {
      "type": "text",
      "content": "West of the Solar Tower is a body, at the base of a billboard."
    },
    "display_order": 15,
    "images": [
      {
        "url": "/assets/images/Wasteland/1-BarrenLands/16-Memorystick-Legionnaire 323's Warning.1.jpg",
        "alt": "Memorystick (Legionnaire 323's Warning)",
        "order": 1
      },
      {
        "url": "/assets/images/Wasteland/1-BarrenLands/16-Memorystick-Legionnaire 323's Warning.2.jpg",
        "alt": "Memorystick (Legionnaire 323's Warning)",
        "order": 2
      }
    ]
  },
  {
    "id": 587,
    "level": "Wasteland",
    "location": "Barren Lands",
    "types": [
      "Can"
    ],
    "title": "Can - Potential Tempest",
    "description": {
      "type": "text",
      "content": "Turn on 2 consoles in the area north of the Solar Tower, then push the yellow box to the shipping container in the middle of the area to turn on the final console. The chest next to it will open, which has this can inside."
    },
    "display_order": 16,
    "images": [
      {
        "url": "/assets/images/Wasteland/1-BarrenLands/17-Can-Potential Tempest.1.jpg",
        "alt": "Can - Potential Tempest",
        "order": 1
      },
      {
        "url": "/assets/images/Wasteland/1-BarrenLands/17-Can-Potential Tempest.2.jpg",
        "alt": "Can - Potential Tempest",
        "order": 2
      },
      {
        "url": "/assets/images/Wasteland/1-BarrenLands/17-Can-Potential Tempest.3.jpg",
        "alt": "Can - Potential Tempest",
        "order": 3
      },
      {
        "url": "/assets/images/Wasteland/1-BarrenLands/17-Can-Potential Tempest.4.jpg",
        "alt": "Can - Potential Tempest",
        "order": 4
      },
      {
        "url": "/assets/images/Wasteland/1-BarrenLands/17-Can-Potential Tempest.5.jpg",
        "alt": "Can - Potential Tempest",
        "order": 5
      }
    ]
  },
  {
    "id": 588,
    "level": "Wasteland",
    "location": "Barren Lands",
    "types": [
      "Memorystick"
    ],
    "title": "Memorystick (The Search for a Haven)",
    "description": {
      "type": "text",
      "content": "Head northeast of the Solar Tower and climb the cliffs up to the large open area to the northwest. There's a corpse at the entrance."
    },
    "display_order": 17,
    "images": [
      {
        "url": "/assets/images/Wasteland/1-BarrenLands/18-Memorystick-The Search for a Haven.1.jpg",
        "alt": "Memorystick (The Search for a Haven)",
        "order": 1
      },
      {
        "url": "/assets/images/Wasteland/1-BarrenLands/18-Memorystick-The Search for a Haven.2.jpg",
        "alt": "Memorystick (The Search for a Haven)",
        "order": 2
      }
    ]
  },
  {
    "id": 589,
    "level": "Wasteland",
    "location": "Barren Lands",
    "types": [
      "Outfit"
    ],
    "title": "Lily Outfit - Rainy Day",
    "description": {
      "type": "text",
      "content": "North of the previous memorystick, in the haven. Underwater. Ignore the other chest for now (the locked one), as that's part of another quest later on when you have the Fishing Rod."
    },
    "display_order": 18,
    "images": [
      {
        "url": "/assets/images/Wasteland/1-BarrenLands/19-Lily Outfit-Rainy Day.1.jpg",
        "alt": "Lily Outfit (Rainy Day)",
        "order": 1
      },
      {
        "url": "/assets/images/Wasteland/1-BarrenLands/19-Lily Outfit-Rainy Day.2.jpg",
        "alt": "Lily Outfit (Rainy Day)",
        "order": 2
      },
      {
        "url": "/assets/images/Wasteland/1-BarrenLands/19-Lily Outfit-Rainy Day.3.jpg",
        "alt": "Lily Outfit (Rainy Day)",
        "order": 3
      }
    ]
  },
  {
    "id": 590,
    "level": "Wasteland",
    "location": "Barren Lands",
    "types": [
      "Nano Suit"
    ],
    "title": "Nano Suit - Racer's High",
    "description": {
      "type": "text",
      "content": "Head back out from the haven, go east and drop down onto the rocks for this Nano Suit."
    },
    "display_order": 19,
    "images": [
      {
        "url": "/assets/images/Wasteland/1-BarrenLands/20-Nano Suit-Racer's High.1.jpg",
        "alt": "Nano Suit - Racer's High",
        "order": 1
      },
      {
        "url": "/assets/images/Wasteland/1-BarrenLands/20-Nano Suit-Racer's High.2.jpg",
        "alt": "Nano Suit - Racer's High",
        "order": 2
      }
    ]
  },
  {
    "id": 591,
    "level": "Wasteland",
    "location": "Barren Lands",
    "types": [
      "Camp"
    ],
    "title": "Solar Tower Entrance Supply Camp",
    "description": {
      "type": "text",
      "content": "You'll find this camp east of the Solar Tower."
    },
    "display_order": 20,
    "images": [
      {
        "url": "/assets/images/Wasteland/1-BarrenLands/21-Supply Camp-Solar Tower Entrance.1.jpg",
        "alt": "Solar Tower Entrance Supply Camp",
        "order": 1
      },
      {
        "url": "/assets/images/Wasteland/1-BarrenLands/21-Supply Camp-Solar Tower Entrance.2.jpg",
        "alt": "Solar Tower Entrance Supply Camp",
        "order": 2
      }
    ]
  },
  {
    "id": 592,
    "level": "Wasteland",
    "location": "Barren Lands",
    "types": [
      "Memorystick"
    ],
    "title": "Memorystick (Marco's Recollection)",
    "description": {
      "type": "text",
      "content": "Just to the northeast of the Supply Camp is a human corpse with this memorystick."
    },
    "display_order": 21,
    "images": [
      {
        "url": "/assets/images/Wasteland/1-BarrenLands/22-Memorystick-Marco's Recollection.1.jpg",
        "alt": "Memorystick (Marco's Recollection)",
        "order": 1
      },
      {
        "url": "/assets/images/Wasteland/1-BarrenLands/22-Memorystick-Marco's Recollection.2.jpg",
        "alt": "Memorystick (Marco's Recollection)",
        "order": 2
      }
    ]
  },
  {
    "id": 593,
    "level": "Wasteland",
    "location": "Barren Lands",
    "types": [
      "Robot"
    ],
    "title": "Mind Map Copy",
    "description": {
      "type": "text",
      "content": "Southeast of the Barren Land Legion Camp is a robot with a Mind Map Copy inside. Part of Su and Enya's side quest, “Looking At You.”"
    },
    "display_order": 22,
    "images": [
      {
        "url": "/assets/images/Wasteland/1-BarrenLands/23-Robot-Mind Map Copy.1.jpg",
        "alt": "Robot - Mind Map Copy",
        "order": 1
      },
      {
        "url": "/assets/images/Wasteland/1-BarrenLands/23-Robot-Mind Map Copy.2.jpg",
        "alt": "Robot - Mind Map Copy",
        "order": 2
      }
    ]
  },
  {
    "id": 594,
    "level": "Wasteland",
    "location": "Barren Lands",
    "types": [
      "Robot"
    ],
    "title": "Mind Map Copy",
    "description": {
      "type": "text",
      "content": "East of the Hidden Path Supply Camp is a path that leads to a dead end. It's heavily guarded, and has a robot in the middle. Part of Su and Enya's side quest, “Looking At You.”"
    },
    "display_order": 23,
    "images": [
      {
        "url": "/assets/images/Wasteland/1-BarrenLands/24-Robot-Mind Map Copy.1.jpg",
        "alt": "Robot - Mind Map Copy",
        "order": 1
      },
      {
        "url": "/assets/images/Wasteland/1-BarrenLands/24-Robot-Mind Map Copy.2.jpg",
        "alt": "Robot - Mind Map Copy",
        "order": 2
      }
    ]
  },
  {
    "id": 595,
    "level": "Wasteland",
    "location": "Barren Lands",
    "types": [
      "Exospine"
    ],
    "title": "Impact-Type Exospine",
    "description": {
      "type": "text",
      "content": "Defeat the three waves of enemies in the small arena to the north of the Robot and you'll find this in the case at the end."
    },
    "display_order": 24,
    "images": [
      {
        "url": "/assets/images/Wasteland/1-BarrenLands/26-Impact-Type Exospine.1.jpg",
        "alt": "Impact-Type Exospine",
        "order": 1
      },
      {
        "url": "/assets/images/Wasteland/1-BarrenLands/26-Impact-Type Exospine.2.jpg",
        "alt": "Impact-Type Exospine",
        "order": 2
      }
    ]
  },
  {
    "id": 596,
    "level": "Wasteland",
    "location": "Barren Lands",
    "types": [
      "Memorystick"
    ],
    "title": "Memorystick (Scavenger 248's Despair)",
    "description": {
      "type": "text",
      "content": "South of the previous area. On the cliffs to the west."
    },
    "display_order": 25,
    "images": [
      {
        "url": "/assets/images/Wasteland/1-BarrenLands/27-Memorystick-Scavenger 248's Despair.1.jpg",
        "alt": "Memorystick (Scavenger 248's Despair)",
        "order": 1
      },
      {
        "url": "/assets/images/Wasteland/1-BarrenLands/27-Memorystick-Scavenger 248's Despair.2.jpg",
        "alt": "Memorystick (Scavenger 248's Despair)",
        "order": 2
      }
    ]
  },
  {
    "id": 597,
    "level": "Wasteland",
    "location": "Barren Lands",
    "types": [
      "Supply Box"
    ],
    "title": "Legion Supply Box",
    "description": {
      "type": "text",
      "content": "East of the previous memorystick. At the end of a small dead end."
    },
    "display_order": 26,
    "images": [
      {
        "url": "/assets/images/Wasteland/1-BarrenLands/28-Legion Supply Box.1.jpg",
        "alt": "Legion Supply Box",
        "order": 1
      },
      {
        "url": "/assets/images/Wasteland/1-BarrenLands/28-Legion Supply Box.2.jpg",
        "alt": "Legion Supply Box",
        "order": 2
      }
    ]
  },
  {
    "id": 598,
    "level": "Wasteland",
    "location": "Barren Lands",
    "types": [
      "Memorystick"
    ],
    "title": "Memorystick (Sentinel 82's Report)",
    "description": {
      "type": "text",
      "content": "South of the previous supply crate, just jump down the cliff and it's by an enemy or two."
    },
    "display_order": 27,
    "images": [
      {
        "url": "/assets/images/Wasteland/1-BarrenLands/30-Memorystick-Sentinel 82's Report.1.jpg",
        "alt": "Memorystick (Sentinel 82's Report)",
        "order": 1
      },
      {
        "url": "/assets/images/Wasteland/1-BarrenLands/30-Memorystick-Sentinel 82's Report.2.jpg",
        "alt": "Memorystick (Sentinel 82's Report)",
        "order": 2
      }
    ]
  },
  {
    "id": 599,
    "level": "Wasteland",
    "location": "Barren Lands",
    "types": [
      "Memorystick"
    ],
    "title": "Memorystick (Scavenger 131's Memory)",
    "description": {
      "type": "text",
      "content": "South of the previous memorystick, in the southeast corner of the dead end area."
    },
    "display_order": 28,
    "images": [
      {
        "url": "/assets/images/Wasteland/1-BarrenLands/29-Memorystick-Scavenger 131's Memory.1.jpg",
        "alt": "Memorystick (Scavenger 131's Memory)",
        "order": 1
      },
      {
        "url": "/assets/images/Wasteland/1-BarrenLands/29-Memorystick-Scavenger 131's Memory.2.jpg",
        "alt": "Memorystick (Scavenger 131's Memory)",
        "order": 2
      }
    ]
  },
  {
    "id": 600,
    "level": "Wasteland",
    "location": "Barren Lands",
    "types": [
      "Can"
    ],
    "title": "Can - GrainT Corn",
    "description": {
      "type": "text",
      "content": "On the eastern path from the previous items (the path that leads to Altess Levoire)"
    },
    "display_order": 29,
    "images": [
      {
        "url": "/assets/images/Wasteland/1-BarrenLands/31-Can-GrainT Corn.1.jpg",
        "alt": "Can - GrainT Corn",
        "order": 1
      },
      {
        "url": "/assets/images/Wasteland/1-BarrenLands/31-Can-GrainT Corn.2.jpg",
        "alt": "Can - GrainT Corn",
        "order": 2
      },
      {
        "url": "/assets/images/Wasteland/1-BarrenLands/31-Can-GrainT Corn.3.jpg",
        "alt": "Can - GrainT Corn",
        "order": 3
      }
    ]
  }
]